unify_package/__init__.py
unify_package/convert_color_unify.py
unify_package/dark_mode.py
unify_package/find_gradle_file.py
unify_package/find_nearest_hex_color.py
unify_package/get_child_module.py
unify_package/ignore_module.py
unify_package/replace_custom_color_with_unify.py
unify_package/replace_hardcode_color_with_unify.py
unify_package/replace_neutral_to_unify_new.py
unify_package/utils.py
unify_package/dataset/FinalCustomColor.csv
unify_package/dataset/color-mapper.csv
unify_package/dataset/neutral_to_unify.csv
unify_package/dataset/rgb_dataset.csv
unify_script-0.1.4.4.dist-info/LICENSE
unify_script-0.1.4.4.dist-info/METADATA
unify_script-0.1.4.4.dist-info/WHEEL
unify_script-0.1.4.4.dist-info/top_level.txt
unify_script-0.1.4.4.dist-info/RECORD
