Metadata-Version: 2.1
Name: unify-script
Version: 0.1.4.4
Summary: Unify color script automation converter
Home-page: UNKNOWN
Author: Lukas Kristianto | Yehezkiel
Author-email: lukas.kristianto@tokopedia.com
License: UNKNOWN
Platform: UNKNOWN
Requires-Python: >=3.6
Requires-Dist: numpy
Requires-Dist: webcolors
Requires-Dist: scipy
Requires-Dist: pathlib
